dockvirt/__init__.py
dockvirt/cli.py
dockvirt/vm_manager.py
dockvirt/templates/Caddyfile.j2
dockvirt/templates/cloud-init.yaml.j2
dockvirt/templates/docker-compose.yml.j2
dockvirt_libvirt-0.1.0.dist-info/licenses/LICENSE
dockvirt_libvirt-0.1.0.dist-info/METADATA
dockvirt_libvirt-0.1.0.dist-info/WHEEL
dockvirt_libvirt-0.1.0.dist-info/entry_points.txt
dockvirt_libvirt-0.1.0.dist-info/top_level.txt
dockvirt_libvirt-0.1.0.dist-info/RECORD
