Metadata-Version: 2.4
Name: dockvirt-libvirt
Version: 0.1.0
Summary: Uruchamianie środowisk dynadock + Caddy w izolowanych VM tworzonych przez libvirt/KVM.
Author-email: Cascade <cascade@windsurf.ai>
Classifier: Programming Language :: Python :: 3
Classifier: License :: OSI Approved :: MIT License
Classifier: Operating System :: OS Independent
Requires-Python: >=3.8
License-File: LICENSE
Requires-Dist: click
Requires-Dist: jinja2
Requires-Dist: libvirt-python
Dynamic: license-file
